positionbt/__init__.py
positionbt/core/__init__.py
positionbt/core/backtester.py
positionbt/core/constants.py
positionbt/indicators/__init__.py
positionbt/indicators/base.py
positionbt/indicators/indicators.py
positionbt/indicators/registry.py
positionbt/models/__init__.py
positionbt/models/models.py
positionbt/utils/__init__.py
positionbt/utils/validation.py
positionbt/visualization/__init__.py
positionbt/visualization/base.py
positionbt/visualization/figures.py
positionbt/visualization/registry.py
positionbt/visualization/visualizer.py
positionbt/visualization/templates/report_template.html
positionbt-1.3.2.dist-info/licenses/LICENSE
positionbt-1.3.2.dist-info/METADATA
positionbt-1.3.2.dist-info/WHEEL
positionbt-1.3.2.dist-info/top_level.txt
positionbt-1.3.2.dist-info/RECORD
