Metadata-Version: 2.4
Name: positionbt
Version: 1.3.2
Summary: PositionBT is a simple, fast, and customizable backtesting framework that directly evaluates trading strategies through position data (ranging from -1 to 1).
Home-page: https://github.com/xuanronaldo/positionbt
Author: Xuan Ronaldo
Author-email: xuanronaldo@outlook.com
Classifier: Programming Language :: Python :: 3
Classifier: License :: OSI Approved :: MIT License
Classifier: Operating System :: OS Independent
Requires-Python: >=3.10
License-File: LICENSE
Requires-Dist: polars>=1.13.0
Requires-Dist: pandas>=2.0.0
Requires-Dist: plotly>=5.18.0
Dynamic: author
Dynamic: author-email
Dynamic: classifier
Dynamic: home-page
Dynamic: license-file
Dynamic: requires-dist
Dynamic: requires-python
Dynamic: summary
